datacraft_faker/__init__.py
datacraft_faker/py.typed
datacraft_faker-0.2.0.dist-info/LICENSE
datacraft_faker-0.2.0.dist-info/METADATA
datacraft_faker-0.2.0.dist-info/WHEEL
datacraft_faker-0.2.0.dist-info/entry_points.txt
datacraft_faker-0.2.0.dist-info/top_level.txt
datacraft_faker-0.2.0.dist-info/RECORD
