Metadata-Version: 2.2
Name: datacraft-faker
Version: 0.2.0
Summary: Custom faker type extensions for datacraft package
Home-page: https://github.com/bbux-dev/datacraft-faker
Author: Brian Buxton
Author-email: bbux-dev@gmail.com
License: MIT
License-File: LICENSE
Requires-Dist: datacraft>=0.7.1
Requires-Dist: faker
Provides-Extra: test
Requires-Dist: pytest>=6.2.2; extra == "test"
Requires-Dist: pycodestyle; extra == "test"
Requires-Dist: pytest-cov; extra == "test"
Requires-Dist: faker-vehicle; extra == "test"
Provides-Extra: all
Requires-Dist: pytest>=6.2.2; extra == "all"
Requires-Dist: pycodestyle; extra == "all"
Requires-Dist: pytest-cov; extra == "all"
Requires-Dist: faker-vehicle; extra == "all"
